[
   {
      "lineIndex":1,
      "id":"NULL",
      "line":"\"Welcome.\"",
      "parameter":"-1",
      "functionTrue":false
   },
   {
      "lineIndex":2,
      "id":"NULL",
      "line":"\"You are currently playing Cafe Lajoie ver.0.1.2 demo edition.\"",
      "parameter":"-1",
      "functionTrue":false
   },
   {
      "lineIndex":3,
      "id":"NULL",
      "line":"\"Yes, it is still a demo version.\"",
      "parameter":"-1",
      "functionTrue":false
   },
   {
      "lineIndex":4,
      "id":"NULL",
      "line":"\"Progress has been tough these last months, and further development will prove to be a hard one.\"",
      "parameter":"-1",
      "functionTrue":false
   },
   {
      "lineIndex":5,
      "id":"NULL",
      "line":"\"Since we do not want to keep you waiting until the full release...\"",
      "parameter":"-1",
      "functionTrue":false
   },
   {
      "lineIndex":6,
      "id":"NULL",
      "line":"\"As a freebees, we are giving you a small taste of what to come\"",
      "parameter":"-1",
      "functionTrue":false
   },
   {
      "lineIndex":7,
      "id":"NULL",
      "line":"\"Without further a do, please enjoy your time at Cafe Lajoie. Signed Rein Freebird\"",
      "parameter":"-1",
      "functionTrue":false
   },
   {
      "lineIndex":8,
      "id":"NULL",
      "line":"",
      "parameter":"-1",
      "functionTrue":false
   },
   {
      "lineIndex":9,
      "id":"F",
      "line":"Fade_BG",
      "parameter":"0",
      "functionTrue":true
   },
   {
      "lineIndex":10,
      "id":"F",
      "line":"Play_Music",
      "parameter":"0",
      "functionTrue":true
   },
   {
      "lineIndex":11,
      "id":"Miyuki",
      "line":"\"Welcome\"",
      "parameter":"1",
      "functionTrue":false
   },
   {
      "lineIndex":12,
      "id":"Mizuo",
      "line":"\"Welcome\"",
      "parameter":"1",
      "functionTrue":false
   },
   {
      "lineIndex":13,
      "id":"Mizuo",
      "line":"\"Ah, a new face. Is this your first time coming here?\"",
      "parameter":"1",
      "functionTrue":false
   },
   {
      "lineIndex":14,
      "id":"F",
      "line":"Selection",
      "parameter":"2",
      "functionTrue":true
   },
   {
      "lineIndex":15,
      "id":"S",
      "line":"\"Yes\"",
      "parameter":"17",
      "functionTrue":true
   },
   {
      "lineIndex":16,
      "id":"S",
      "line":"\"Kinda\"",
      "parameter":"23",
      "functionTrue":true
   },
   {
      "lineIndex":17,
      "id":"Miyuki",
      "line":"\"Ah, right. I have never seen you before.\"",
      "parameter":"2",
      "functionTrue":false
   },
   {
      "lineIndex":18,
      "id":"Miyuki",
      "line":"\"Yay, we got a new customer.\"",
      "parameter":"1",
      "functionTrue":false
   },
   {
      "lineIndex":19,
      "id":"Miyuki",
      "line":"\"Celebration... DANCE!!\"",
      "parameter":"9",
      "functionTrue":false
   },
   {
      "lineIndex":20,
      "id":"Mizuo",
      "line":"\"...\"",
      "parameter":"5",
      "functionTrue":false
   },
   {
      "lineIndex":21,
      "id":"Mizuo",
      "line":"\"Pardon my coleague, she tends to get over excited at times.\"",
      "parameter":"2",
      "functionTrue":false
   },
   {
      "lineIndex":22,
      "id":"F",
      "line":"Jump_to_Line",
      "parameter":"30",
      "functionTrue":true
   },
   {
      "lineIndex":23,
      "id":"Mizuo",
      "line":"\"Kinda?\"",
      "parameter":"1",
      "functionTrue":false
   },
   {
      "lineIndex":24,
      "id":"Mizuo",
      "line":"\"Ah, perhaps we weren't here when you came by.\"",
      "parameter":"2",
      "functionTrue":false
   },
   {
      "lineIndex":25,
      "id":"Mizuo",
      "line":"\"What about you, Miyuki? Something came in mind\"",
      "parameter":"1",
      "functionTrue":false
   },
   {
      "lineIndex":26,
      "id":"Miyuki",
      "line":"\"Yeah, i've seen you here before...\"",
      "parameter":"2",
      "functionTrue":false
   },
   {
      "lineIndex":27,
      "id":"Miyuki",
      "line":"\"..I think.\"",
      "parameter":"3",
      "functionTrue":false
   },
   {
      "lineIndex":28,
      "id":"Mizuo",
      "line":"\"You think...?\"",
      "parameter":"5",
      "functionTrue":false
   },
   {
      "lineIndex":29,
      "id":"Mizuo",
      "line":"\"Well, whatever\"",
      "parameter":"3",
      "functionTrue":false
   },
   {
      "lineIndex":30,
      "id":"Mizuo",
      "line":"\"Any how, that you are here somehow, there's something important the I need to tell you.\"",
      "parameter":"1",
      "functionTrue":false
   },
   {
      "lineIndex":31,
      "id":"Mizuo",
      "line":"\"Sadly to say, we are currently not open for business, therefore we can't take your order yet.\"",
      "parameter":"3",
      "functionTrue":false
   },
   {
      "lineIndex":32,
      "id":"Miyuki",
      "line":"\"We're sorry, you took your time to get here.\"",
      "parameter":"5",
      "functionTrue":false
   },
   {
      "lineIndex":33,
      "id":"Miyuki",
      "line":"\"We understand if you are dissapointed.\"",
      "parameter":"5",
      "functionTrue":false
   },
   {
      "lineIndex":34,
      "id":"Mizuo",
      "line":"\"That being said, it's okay if you want to go back now.\"",
      "parameter":"1",
      "functionTrue":false
   },
   {
      "lineIndex":35,
      "id":"Mizuo",
      "line":"\"Or if you want to, you can stay here for a while. You might found out what you want to do later.\"",
      "parameter":"1",
      "functionTrue":false
   },
   {
      "lineIndex":36,
      "id":"Miyuki",
      "line":"\"Hey, that's a great idea.\"",
      "parameter":"4",
      "functionTrue":false
   },
   {
      "lineIndex":37,
      "id":"Miyuki",
      "line":"\"We can talk about things, play some games, and maybe do things more than that.\"",
      "parameter":"4",
      "functionTrue":false
   },
   {
      "lineIndex":38,
      "id":"Mizuo",
      "line":"\"What do you say? Stay with us for a while, we'll make it worth a while for you\"",
      "parameter":"3",
      "functionTrue":false
   },
   {
      "lineIndex":39,
      "id":"F",
      "line":"Selection",
      "parameter":"2",
      "functionTrue":true
   },
   {
      "lineIndex":40,
      "id":"S",
      "line":"\"Sure\"",
      "parameter":"47",
      "functionTrue":true
   },
   {
      "lineIndex":41,
      "id":"S",
      "line":"\"Maybe next time\"",
      "parameter":"42",
      "functionTrue":true
   },
   {
      "lineIndex":42,
      "id":"Mizuo",
      "line":"\"Ah, is that so...\"",
      "parameter":"3",
      "functionTrue":false
   },
   {
      "lineIndex":43,
      "id":"Mizuo",
      "line":"\"Oh well, I guess we'll see you later.\"",
      "parameter":"2",
      "functionTrue":false
   },
   {
      "lineIndex":44,
      "id":"Miyuki",
      "line":"\"Come back again.\"",
      "parameter":"7",
      "functionTrue":false
   },
   {
      "lineIndex":45,
      "id":"NULL",
      "line":"And so, you leave Cafe Lajoie",
      "parameter":"-1",
      "functionTrue":false
   },
   {
      "lineIndex":46,
      "id":"F",
      "line":"Change_Scene_No_Pref",
      "parameter":"0",
      "functionTrue":true
   },
   {
      "lineIndex":47,
      "id":"Mizuo",
      "line":"\"Ah, great then.\"",
      "parameter":"1",
      "functionTrue":false
   },
   {
      "lineIndex":48,
      "id":"Miyuki",
      "line":"\"Yeay, It's going to be a lot of fun.\"",
      "parameter":"1",
      "functionTrue":false
   },
   {
      "lineIndex":49,
      "id":"Mizuo",
      "line":"\"Hm... What should we do I wonder\"",
      "parameter":"2",
      "functionTrue":false
   },
   {
      "lineIndex":50,
      "id":"Miyuki",
      "line":"\"I know, let's have a chat for a bit.\"",
      "parameter":"3",
      "functionTrue":false
   },
   {
      "lineIndex":51,
      "id":"Miyuki",
      "line":"\"Then we can play something together.\"",
      "parameter":"1",
      "functionTrue":false
   },
   {
      "lineIndex":52,
      "id":"Mizuo",
      "line":"\"Well, I'm okay with anything.\"",
      "parameter":"2",
      "functionTrue":false
   },
   {
      "lineIndex":53,
      "id":"Mizuo",
      "line":"\"Ah, I almost forgot.\"",
      "parameter":"3",
      "functionTrue":false
   },
   {
      "lineIndex":54,
      "id":"Mizuo",
      "line":"\"We haven't introduced ourselves right?.\"",
      "parameter":"1",
      "functionTrue":false
   },
   {
      "lineIndex":55,
      "id":"Miyuki",
      "line":"\"Let me do it first.\"",
      "parameter":"4",
      "functionTrue":false
   },
   {
      "lineIndex":56,
      "id":"Miyuki",
      "line":"\"Hi, I'm Miyuki. Nice to meet you.\"",
      "parameter":"3",
      "functionTrue":false
   },
   {
      "lineIndex":57,
      "id":"Mizuo",
      "line":"\"Well, I'm Mizuo. Pleasure's mine.\"",
      "parameter":"2",
      "functionTrue":false
   },
   {
      "lineIndex":58,
      "id":"Miyuki",
      "line":"\"Well, what do you want to talk about?\"",
      "parameter":"2",
      "functionTrue":false
   },
   {
      "lineIndex":59,
      "id":"F",
      "line":"Selection",
      "parameter":"5",
      "functionTrue":true
   },
   {
      "lineIndex":60,
      "id":"S",
      "line":"Talk about Cafe Lajoie",
      "parameter":"65",
      "functionTrue":true
   },
   {
      "lineIndex":61,
      "id":"S",
      "line":"Talk about the games",
      "parameter":"75",
      "functionTrue":true
   },
   {
      "lineIndex":62,
      "id":"S",
      "line":"Talk with Miyuki",
      "parameter":"81",
      "functionTrue":true
   },
   {
      "lineIndex":63,
      "id":"S",
      "line":"Talk with Mizuo",
      "parameter":"113",
      "functionTrue":true
   },
   {
      "lineIndex":64,
      "id":"S",
      "line":"Let's play",
      "parameter":"144",
      "functionTrue":true
   },
   {
      "lineIndex":65,
      "id":"Mizuo",
      "line":"\"Well, Cafe Lajoie is a cafe, if I couldn't be more obvious.\"",
      "parameter":"2",
      "functionTrue":false
   },
   {
      "lineIndex":66,
      "id":"Mizuo",
      "line":"\"Though we call it a cafe, it's more of a family restaurant really.\"",
      "parameter":"1",
      "functionTrue":false
   },
   {
      "lineIndex":67,
      "id":"Miyuki",
      "line":"\"We serve customers with our home-made style food, giving the feeling at home.\"",
      "parameter":"2",
      "functionTrue":false
   },
   {
      "lineIndex":68,
      "id":"Miyuki",
      "line":"\"Stuffed stomach and a smile on your face, that's our priorities\"",
      "parameter":"1",
      "functionTrue":false
   },
   {
      "lineIndex":69,
      "id":"Miyuki",
      "line":"\"We've only opened just recently, so we're pretty new here\"",
      "parameter":"2",
      "functionTrue":false
   },
   {
      "lineIndex":70,
      "id":"Miyuki",
      "line":"\"Even so, we're ready to serve you.\"",
      "parameter":"1",
      "functionTrue":false
   },
   {
      "lineIndex":71,
      "id":"Mizuo",
      "line":"\"That on normal ocassion, we're not serving today.\"",
      "parameter":"2",
      "functionTrue":false
   },
   {
      "lineIndex":72,
      "id":"Mizuo",
      "line":"\"I personally don't know when we'll be able to start serving, I hope it start as soon as possible.\"",
      "parameter":"1",
      "functionTrue":false
   },
   {
      "lineIndex":73,
      "id":"Miyuki",
      "line":"\"Yeah, I can't wait too.\"",
      "parameter":"3",
      "functionTrue":false
   },
   {
      "lineIndex":74,
      "id":"F",
      "line":"Jump_to_Line",
      "parameter":"59",
      "functionTrue":true
   },
   {
      "lineIndex":75,
      "id":"Mizuo",
      "line":"\"Oh yeah, we did mention about a game earlier.\"",
      "parameter":"2",
      "functionTrue":false
   },
   {
      "lineIndex":76,
      "id":"Mizuo",
      "line":"\"Don't want to tell you a whole lot, we'll tell about it after we finish our chat.\"",
      "parameter":"1",
      "functionTrue":false
   },
   {
      "lineIndex":77,
      "id":"Miyuki",
      "line":"\"Basically, besides eating you can also play game here.\"",
      "parameter":"2",
      "functionTrue":false
   },
   {
      "lineIndex":78,
      "id":"Miyuki",
      "line":"\"What kind of game?\"",
      "parameter":"2",
      "functionTrue":false
   },
   {
      "lineIndex":79,
      "id":"Miyuki",
      "line":"\"Just wait until we finish our talking\"",
      "parameter":"1",
      "functionTrue":false
   },
   {
      "lineIndex":80,
      "id":"F",
      "line":"Jump_to_Line",
      "parameter":"59",
      "functionTrue":true
   },
   {
      "lineIndex":81,
      "id":"Miyuki",
      "line":"\"Ah, what do you want to know about me?\"",
      "parameter":"2",
      "functionTrue":false
   },
   {
      "lineIndex":82,
      "id":"F",
      "line":"Selection",
      "parameter":"4",
      "functionTrue":true
   },
   {
      "lineIndex":83,
      "id":"S",
      "line":"What you do",
      "parameter":"87",
      "functionTrue":true
   },
   {
      "lineIndex":84,
      "id":"S",
      "line":"Things you like",
      "parameter":"95",
      "functionTrue":true
   },
   {
      "lineIndex":85,
      "id":"S",
      "line":"Your sizes...",
      "parameter":"101",
      "functionTrue":true
   },
   {
      "lineIndex":86,
      "id":"S",
      "line":"Back",
      "parameter":"111",
      "functionTrue":true
   },
   {
      "lineIndex":87,
      "id":"Miyuki",
      "line":"\"I work here, as a maid.\"",
      "parameter":"3",
      "functionTrue":false
   },
   {
      "lineIndex":88,
      "id":"Miyuki",
      "line":"\"Outside of that, I'm also a high school student.\"",
      "parameter":"3",
      "functionTrue":false
   },
   {
      "lineIndex":89,
      "id":"Miyuki",
      "line":"\"I still haven't decide what will I do after graduation.\"",
      "parameter":"2",
      "functionTrue":false
   },
   {
      "lineIndex":90,
      "id":"Miyuki",
      "line":"\"I could try applying for university.\"",
      "parameter":"2",
      "functionTrue":false
   },
   {
      "lineIndex":91,
      "id":"Miyuki",
      "line":"\"I could continue working here.\"",
      "parameter":"2",
      "functionTrue":false
   },
   {
      "lineIndex":92,
      "id":"Miyuki",
      "line":"\"I could even do both.\"",
      "parameter":"1",
      "functionTrue":false
   },
   {
      "lineIndex":93,
      "id":"Miyuki",
      "line":"\"Which ever I choose, I'll be fine.\"",
      "parameter":"1",
      "functionTrue":false
   },
   {
      "lineIndex":94,
      "id":"F",
      "line":"Jump_to_Line",
      "parameter":"82",
      "functionTrue":true
   },
   {
      "lineIndex":95,
      "id":"Miyuki",
      "line":"\"What I like? Hm...\"",
      "parameter":"2",
      "functionTrue":false
   },
   {
      "lineIndex":96,
      "id":"Miyuki",
      "line":"\"I like to draw a lot.\"",
      "parameter":"3",
      "functionTrue":false
   },
   {
      "lineIndex":97,
      "id":"Miyuki",
      "line":"\"I also write as a hobby.\"",
      "parameter":"2",
      "functionTrue":false
   },
   {
      "lineIndex":98,
      "id":"Miyuki",
      "line":"\"My favorite foods are chocolate and cupcakes. For my drink I like milkshake of any flavor.\"",
      "parameter":"2",
      "functionTrue":false
   },
   {
      "lineIndex":99,
      "id":"Miyuki",
      "line":"\"That's about all\"",
      "parameter":"2",
      "functionTrue":false
   },
   {
      "lineIndex":100,
      "id":"F",
      "line":"Jump_to_Line",
      "parameter":"82",
      "functionTrue":true
   },
   {
      "lineIndex":101,
      "id":"Miyuki",
      "line":"\"Hahaha...\"",
      "parameter":"1",
      "functionTrue":false
   },
   {
      "lineIndex":102,
      "id":"Miyuki",
      "line":"\"I see you're curious of my numbers.\"",
      "parameter":"8",
      "functionTrue":false
   },
   {
      "lineIndex":103,
      "id":"Miyuki",
      "line":"\"I haven't have it measured for a while.\"",
      "parameter":"8",
      "functionTrue":false
   },
   {
      "lineIndex":104,
      "id":"Miyuki",
      "line":"\"Wonder if any number jump out a lot.\"",
      "parameter":"8",
      "functionTrue":false
   },
   {
      "lineIndex":105,
      "id":"Miyuki",
      "line":"\"Would you want to measure it for me?\"",
      "parameter":"8",
      "functionTrue":false
   },
   {
      "lineIndex":106,
      "id":"Mizuo",
      "line":"\"...\"",
      "parameter":"2",
      "functionTrue":false
   },
   {
      "lineIndex":107,
      "id":"Miyuki",
      "line":"\"No, ofcourse you won't.\"",
      "parameter":"2",
      "functionTrue":false
   },
   {
      "lineIndex":108,
      "id":"Miyuki",
      "line":"\"It would be considered sexual harasement.\"",
      "parameter":"3",
      "functionTrue":false
   },
   {
      "lineIndex":109,
      "id":"Miyuki",
      "line":"\"You wouldn't want the cops to come would you?\"",
      "parameter":"8",
      "functionTrue":false
   },
   {
      "lineIndex":110,
      "id":"F",
      "line":"Jump_to_Line",
      "parameter":"82",
      "functionTrue":true
   },
   {
      "lineIndex":111,
      "id":"Miyuki",
      "line":"\"Well, what do you want to talk about?\"",
      "parameter":"2",
      "functionTrue":false
   },
   {
      "lineIndex":112,
      "id":"F",
      "line":"Jump_to_Line",
      "parameter":"59",
      "functionTrue":true
   },
   {
      "lineIndex":113,
      "id":"Mizuo",
      "line":"\"Hm... something you want to ask?\"",
      "parameter":"1",
      "functionTrue":false
   },
   {
      "lineIndex":114,
      "id":"F",
      "line":"Selection",
      "parameter":"4",
      "functionTrue":true
   },
   {
      "lineIndex":115,
      "id":"S",
      "line":"What you do",
      "parameter":"119",
      "functionTrue":true
   },
   {
      "lineIndex":116,
      "id":"S",
      "line":"Things you like",
      "parameter":"126",
      "functionTrue":true
   },
   {
      "lineIndex":117,
      "id":"S",
      "line":"Your number",
      "parameter":"132",
      "functionTrue":true
   },
   {
      "lineIndex":118,
      "id":"S",
      "line":"Back",
      "parameter":"142",
      "functionTrue":true
   },
   {
      "lineIndex":119,
      "id":"Mizuo",
      "line":"\"I work here as a chef, if you couldn't figure out by my clothes yet.\"",
      "parameter":"1",
      "functionTrue":false
   },
   {
      "lineIndex":120,
      "id":"Mizuo",
      "line":"\"Outside I'm a student at University, studying Computer Science.\"",
      "parameter":"1",
      "functionTrue":false
   },
   {
      "lineIndex":121,
      "id":"Mizuo",
      "line":"\"Right now I'm taking a break from university, something came up and I couldn't keep things situated .\"",
      "parameter":"3",
      "functionTrue":false
   },
   {
      "lineIndex":122,
      "id":"Mizuo",
      "line":"\"After everything is settled, I took this job to keep my self occupied.\"",
      "parameter":"2",
      "functionTrue":false
   },
   {
      "lineIndex":123,
      "id":"Mizuo",
      "line":"\"I'm planning to resume my study next year.\"",
      "parameter":"1",
      "functionTrue":false
   },
   {
      "lineIndex":124,
      "id":"Mizuo",
      "line":"\"So yeah, there you go.\"",
      "parameter":"2",
      "functionTrue":false
   },
   {
      "lineIndex":125,
      "id":"F",
      "line":"Jump_to_Line",
      "parameter":"114",
      "functionTrue":true
   },
   {
      "lineIndex":126,
      "id":"Mizuo",
      "line":"\"What I like?\"",
      "parameter":"1",
      "functionTrue":false
   },
   {
      "lineIndex":127,
      "id":"Mizuo",
      "line":"\"If you're talking about food or drinks, I don't have any\"",
      "parameter":"1",
      "functionTrue":false
   },
   {
      "lineIndex":128,
      "id":"Mizuo",
      "line":"\"I don't have particular food that I really enjoy.\"",
      "parameter":"2",
      "functionTrue":false
   },
   {
      "lineIndex":129,
      "id":"Mizuo",
      "line":"\"Same goes to drink.\"",
      "parameter":"1",
      "functionTrue":false
   },
   {
      "lineIndex":130,
      "id":"Mizuo",
      "line":"\"There just food and drink to me, nothing more.\"",
      "parameter":"2",
      "functionTrue":false
   },
   {
      "lineIndex":131,
      "id":"F",
      "line":"Jump_to_Line",
      "parameter":"114",
      "functionTrue":true
   },
   {
      "lineIndex":132,
      "id":"Mizuo",
      "line":"\"My number?\"",
      "parameter":"1",
      "functionTrue":false
   },
   {
      "lineIndex":133,
      "id":"Mizuo",
      "line":"\"Sure.\"",
      "parameter":"2",
      "functionTrue":false
   },
   {
      "lineIndex":134,
      "id":"Mizuo",
      "line":"\"It's 0812-XXXX5179.\"",
      "parameter":"2",
      "functionTrue":false
   },
   {
      "lineIndex":135,
      "id":"Mizuo",
      "line":"\"Again...\"",
      "parameter":"1",
      "functionTrue":false
   },
   {
      "lineIndex":136,
      "id":"Mizuo",
      "line":"\"XXXX-8012XXXX.\"",
      "parameter":"1",
      "functionTrue":false
   },
   {
      "lineIndex":137,
      "id":"Mizuo",
      "line":"\"...\"",
      "parameter":"1",
      "functionTrue":false
   },
   {
      "lineIndex":138,
      "id":"Mizuo",
      "line":"\"What, you expect me to give it so easily?\"",
      "parameter":"7",
      "functionTrue":false
   },
   {
      "lineIndex":139,
      "id":"Mizuo",
      "line":"\"No, you have to work to actually get it.\"",
      "parameter":"7",
      "functionTrue":false
   },
   {
      "lineIndex":140,
      "id":"Mizuo",
      "line":"\"Don't worry, you can ask as many times as you.\"",
      "parameter":"7",
      "functionTrue":false
   },
   {
      "lineIndex":141,
      "id":"F",
      "line":"Jump_to_Line",
      "parameter":"114",
      "functionTrue":true
   },
   {
      "lineIndex":142,
      "id":"Mizuo",
      "line":"\"Anything else?\"",
      "parameter":"2",
      "functionTrue":false
   },
   {
      "lineIndex":143,
      "id":"F",
      "line":"Jump_to_Line",
      "parameter":"59",
      "functionTrue":true
   },
   {
      "lineIndex":144,
      "id":"Miyuki",
      "line":"\"Yay, let's play now.\"",
      "parameter":"1",
      "functionTrue":false
   },
   {
      "lineIndex":145,
      "id":"Mizuo",
      "line":"\"Right, might as well tell you about this now.\"",
      "parameter":"2",
      "functionTrue":false
   },
   {
      "lineIndex":146,
      "id":"Mizuo",
      "line":"\"We at Cafe Lajoie prioritize ourself on giving the best experience to our customers.\"",
      "parameter":"1",
      "functionTrue":false
   },
   {
      "lineIndex":147,
      "id":"Mizuo",
      "line":"\"Not only we serve food to our patrons table, we also have game sessions where you can play with one of our employee.\"",
      "parameter":"1",
      "functionTrue":false
   },
   {
      "lineIndex":148,
      "id":"Mizuo",
      "line":"\"You can play with other customers as well.\"",
      "parameter":"1",
      "functionTrue":false
   },
   {
      "lineIndex":149,
      "id":"Miyuki",
      "line":"\"Every time you play with us, you'll get points to collect, that you can later trade for something cool.\"",
      "parameter":"2",
      "functionTrue":false
   },
   {
      "lineIndex":150,
      "id":"Miyuki",
      "line":"\"For every employee you play with, you get to play all different games.\"",
      "parameter":"2",
      "functionTrue":false
   },
   {
      "lineIndex":151,
      "id":"Miyuki",
      "line":"\"You might be wonder what I meant by that.\"",
      "parameter":"2",
      "functionTrue":false
   },
   {
      "lineIndex":152,
      "id":"Mizuo",
      "line":"\"To put it simply, the game that you'll play with me will be different from Miyuki's.\"",
      "parameter":"2",
      "functionTrue":false
   },
   {
      "lineIndex":153,
      "id":"Miyuki",
      "line":"\"My game is a game where we crush candies together.\"",
      "parameter":"1",
      "functionTrue":false
   },
   {
      "lineIndex":154,
      "id":"Miyuki",
      "line":"\"Although mine we crush foods and drinks instead of candies.\"",
      "parameter":"2",
      "functionTrue":false
   },
   {
      "lineIndex":155,
      "id":"Miyuki",
      "line":"\"If you like to match things together, you'll love this game.\"",
      "parameter":"1",
      "functionTrue":false
   },
   {
      "lineIndex":156,
      "id":"Mizuo",
      "line":"\"Well, mine is a card base high and low guessing game.\"",
      "parameter":"1",
      "functionTrue":false
   },
   {
      "lineIndex":157,
      "id":"Mizuo",
      "line":"\"It's a gambling game, I know. As long as we don't bet on real money, it should be fine.\"",
      "parameter":"2",
      "functionTrue":false
   },
   {
      "lineIndex":158,
      "id":"Mizuo",
      "line":"\"If you're feeling lucky, why not give it a shot.\"",
      "parameter":"1",
      "functionTrue":false
   },
   {
      "lineIndex":159,
      "id":"Miyuki",
      "line":"\"So, which one would you want to play with?.\"",
      "parameter":"2",
      "functionTrue":false
   },
   {
      "lineIndex":160,
      "id":"F",
      "line":"Selection",
      "parameter":"2",
      "functionTrue":true
   },
   {
      "lineIndex":161,
      "id":"S",
      "line":"Play with Miyuki",
      "parameter":"163",
      "functionTrue":true
   },
   {
      "lineIndex":162,
      "id":"S",
      "line":"Play with Mizuo",
      "parameter":"181",
      "functionTrue":true
   },
   {
      "lineIndex":163,
      "id":"Miyuki",
      "line":"\"You want to play with me? Yay\"",
      "parameter":"1",
      "functionTrue":false
   },
   {
      "lineIndex":164,
      "id":"Miyuki",
      "line":"\"Come on, let's start\"",
      "parameter":"3",
      "functionTrue":false
   },
   {
      "lineIndex":165,
      "id":"F",
      "line":"Change_Scene_With_Pref",
      "parameter":"3",
      "functionTrue":true
   },
   {
      "lineIndex":166,
      "id":"F",
      "line":"Fade_BG",
      "parameter":"0",
      "functionTrue":true
   },
   {
      "lineIndex":167,
      "id":"F",
      "line":"Play_Music",
      "parameter":"0",
      "functionTrue":true
   },
   {
      "lineIndex":168,
      "id":"Miyuki",
      "line":"\"Yay, you finished the game\"",
      "parameter":"1",
      "functionTrue":false
   },
   {
      "lineIndex":169,
      "id":"Miyuki",
      "line":"\"How was it, did you like it?\"",
      "parameter":"2",
      "functionTrue":false
   },
   {
      "lineIndex":170,
      "id":"F",
      "line":"Selection",
      "parameter":"3",
      "functionTrue":true
   },
   {
      "lineIndex":171,
      "id":"S",
      "line":"\"Yes, it was fun.\"",
      "parameter":"174",
      "functionTrue":true
   },
   {
      "lineIndex":172,
      "id":"S",
      "line":"\"It was okay.\"",
      "parameter":"176",
      "functionTrue":true
   },
   {
      "lineIndex":173,
      "id":"S",
      "line":"\"I dont quite enjoy it.\"",
      "parameter":"178",
      "functionTrue":true
   },
   {
      "lineIndex":174,
      "id":"Miyuki",
      "line":"\"Thank you, I'm glad you like it.\"",
      "parameter":"3",
      "functionTrue":false
   },
   {
      "lineIndex":175,
      "id":"F",
      "line":"Jump_to_Line",
      "parameter":"203",
      "functionTrue":true
   },
   {
      "lineIndex":176,
      "id":"Miyuki",
      "line":"\"It was okay? Well, It's not so bad right?\"",
      "parameter":"2",
      "functionTrue":false
   },
   {
      "lineIndex":177,
      "id":"F",
      "line":"Jump_to_Line",
      "parameter":"203",
      "functionTrue":true
   },
   {
      "lineIndex":178,
      "id":"Miyuki",
      "line":"\"Haha... is that so...?\"",
      "parameter":"7",
      "functionTrue":false
   },
   {
      "lineIndex":179,
      "id":"Mizuo",
      "line":"\"...\"",
      "parameter":"5",
      "functionTrue":false
   },
   {
      "lineIndex":180,
      "id":"F",
      "line":"Jump_to_Line",
      "parameter":"203",
      "functionTrue":true
   },
   {
      "lineIndex":181,
      "id":"Mizuo",
      "line":"\"Ah, playing with me? Sure, let's play right away\"",
      "parameter":"1",
      "functionTrue":false
   },
   {
      "lineIndex":182,
      "id":"F",
      "line":"Change_Scene_With_Pref",
      "parameter":"4",
      "functionTrue":true
   },
   {
      "lineIndex":183,
      "id":"F",
      "line":"Fade_BG",
      "parameter":"0",
      "functionTrue":true
   },
   {
      "lineIndex":184,
      "id":"F",
      "line":"Play_Music",
      "parameter":"0",
      "functionTrue":true
   },
   {
      "lineIndex":185,
      "id":"Mizuo",
      "line":"\"Ah, you managed to finished the game.\"",
      "parameter":"1",
      "functionTrue":false
   },
   {
      "lineIndex":186,
      "id":"Mizuo",
      "line":"\"Good for you\"",
      "parameter":"2",
      "functionTrue":false
   },
   {
      "lineIndex":187,
      "id":"F",
      "line":"Jump_to_Line",
      "parameter":"193",
      "functionTrue":true
   },
   {
      "lineIndex":188,
      "id":"F",
      "line":"Fade_BG",
      "parameter":"0",
      "functionTrue":true
   },
   {
      "lineIndex":189,
      "id":"F",
      "line":"Play_Music",
      "parameter":"0",
      "functionTrue":true
   },
   {
      "lineIndex":190,
      "id":"Mizuo",
      "line":"\"Too bad, you went backrupt.\"",
      "parameter":"1",
      "functionTrue":false
   },
   {
      "lineIndex":191,
      "id":"Mizuo",
      "line":"\"Better luck next time\"",
      "parameter":"7",
      "functionTrue":false
   },
   {
      "lineIndex":192,
      "id":"Miyuki",
      "line":"\"...\"",
      "parameter":"3",
      "functionTrue":false
   },
   {
      "lineIndex":193,
      "id":"Mizuo",
      "line":"\"How was it, did you enjoyed our game?\"",
      "parameter":"1",
      "functionTrue":false
   },
   {
      "lineIndex":194,
      "id":"F",
      "line":"Selection",
      "parameter":"3",
      "functionTrue":true
   },
   {
      "lineIndex":195,
      "id":"S",
      "line":"\"Yes, it was fun.\"",
      "parameter":"198",
      "functionTrue":true
   },
   {
      "lineIndex":196,
      "id":"S",
      "line":"\"It was okay.\"",
      "parameter":"200",
      "functionTrue":true
   },
   {
      "lineIndex":197,
      "id":"S",
      "line":"\"I dont quite enjoy it.\"",
      "parameter":"202",
      "functionTrue":true
   },
   {
      "lineIndex":198,
      "id":"Mizuo",
      "line":"\"Ah, glad you like it. Thank you\"",
      "parameter":"2",
      "functionTrue":false
   },
   {
      "lineIndex":199,
      "id":"F",
      "line":"Jump_to_Line",
      "parameter":"203",
      "functionTrue":true
   },
   {
      "lineIndex":200,
      "id":"Mizuo",
      "line":"\"Okay? Okay then.\"",
      "parameter":"2",
      "functionTrue":false
   },
   {
      "lineIndex":201,
      "id":"F",
      "line":"Jump_to_Line",
      "parameter":"203",
      "functionTrue":true
   },
   {
      "lineIndex":202,
      "id":"Mizuo",
      "line":"\"Is that so? I sincerely apologize.\"",
      "parameter":"3",
      "functionTrue":false
   },
   {
      "lineIndex":203,
      "id":"NULL",
      "line":"",
      "parameter":"0",
      "functionTrue":false
   },
   {
      "lineIndex":204,
      "id":"Mizuo",
      "line":"\"Ah, look at the time. It's almost dark already.\"",
      "parameter":"2",
      "functionTrue":false
   },
   {
      "lineIndex":205,
      "id":"Mizuo",
      "line":"\"As much as I want you to stay longer, I'm afraid I have to ask of you to leave.\"",
      "parameter":"1",
      "functionTrue":false
   },
   {
      "lineIndex":206,
      "id":"Mizuo",
      "line":"\"It's the restaurant rule, nothing we can do about it\"",
      "parameter":"3",
      "functionTrue":false
   },
   {
      "lineIndex":207,
      "id":"Miyuki",
      "line":"\"Thank you for coming today.\"",
      "parameter":"1",
      "functionTrue":false
   },
   {
      "lineIndex":208,
      "id":"Miyuki",
      "line":"\"It was fun having you here.\"",
      "parameter":"2",
      "functionTrue":false
   },
   {
      "lineIndex":209,
      "id":"Miyuki",
      "line":"\"See you next time\"",
      "parameter":"1",
      "functionTrue":false
   },
   {
      "lineIndex":210,
      "id":"NULL",
      "line":"Thank you for playing.",
      "parameter":"-1",
      "functionTrue":false
   },
   {
      "lineIndex":211,
      "id":"F",
      "line":"Fade_BG",
      "parameter":"-1",
      "functionTrue":true
   },
   {
      "lineIndex":212,
      "id":"F",
      "line":"Change_Scene_No_Pref",
      "parameter":"0",
      "functionTrue":true
   }
]